pl_sandbox/__about__.py
pl_sandbox/__init__.py
pl_sandbox/my_module.py
lightning_diffusers-0.0.0.dev0.dist-info/LICENSE
lightning_diffusers-0.0.0.dev0.dist-info/METADATA
lightning_diffusers-0.0.0.dev0.dist-info/WHEEL
lightning_diffusers-0.0.0.dev0.dist-info/top_level.txt
lightning_diffusers-0.0.0.dev0.dist-info/RECORD
